[{
        "name": "productB",
        "price": 999902,
        "quantity": 99,
        "image_url": "https://olshop-proto.sgp1.digitaloceanspaces.com/products/MRAjWwhTHc.png"
    },
    {
        "name": "productC",
        "price": 999903,
        "quantity": 99,
        "image_url": "https://olshop-proto.sgp1.digitaloceanspaces.com/products/XVlBzgbaiC.png"
    },
    {
        "name": "productD",
        "price": 999904,
        "quantity": 99,
        "image_url": "https://olshop-proto.sgp1.digitaloceanspaces.com/products/MRAjWwhTHc.png"
    },
    {
        "name": "productE",
        "price": 999905,
        "quantity": 99,
        "image_url": "https://olshop-proto.sgp1.digitaloceanspaces.com/products/XVlBzgbaiC.png"
    },
    {
        "name": "productF",
        "price": 999906,
        "quantity": 99,
        "image_url": "https://olshop-proto.sgp1.digitaloceanspaces.com/products/MRAjWwhTHc.png"
    },
    {
        "name": "productG",
        "price": 999907,
        "quantity": 99,
        "image_url": "https://olshop-proto.sgp1.digitaloceanspaces.com/products/XVlBzgbaiC.png"
    },
    {
        "name": "productH",
        "price": 999908,
        "quantity": 99,
        "image_url": "https://olshop-proto.sgp1.digitaloceanspaces.com/products/MRAjWwhTHc.png"
    },
    {
        "name": "productI",
        "price": 999909,
        "quantity": 99,
        "image_url": "https://olshop-proto.sgp1.digitaloceanspaces.com/products/XVlBzgbaiC.png"
    },
    {
        "name": "productJ",
        "price": 999910,
        "quantity": 99,
        "image_url": "https://olshop-proto.sgp1.digitaloceanspaces.com/products/MRAjWwhTHc.png"
    },
    {
        "name": "productK",
        "price": 999911,
        "quantity": 99,
        "image_url": "https://olshop-proto.sgp1.digitaloceanspaces.com/products/XVlBzgbaiC.png"
    },
    {
        "name": "productL",
        "price": 999912,
        "quantity": 99,
        "image_url": "https://olshop-proto.sgp1.digitaloceanspaces.com/products/MRAjWwhTHc.png"
    },
    {
        "name": "productM",
        "price": 999913,
        "quantity": 99,
        "image_url": "https://olshop-proto.sgp1.digitaloceanspaces.com/products/XVlBzgbaiC.png"
    },
    {
        "name": "productN",
        "price": 999914,
        "quantity": 99,
        "image_url": "https://olshop-proto.sgp1.digitaloceanspaces.com/products/MRAjWwhTHc.png"
    },
    {
        "name": "productO",
        "price": 999915,
        "quantity": 99,
        "image_url": "https://olshop-proto.sgp1.digitaloceanspaces.com/products/XVlBzgbaiC.png"
    },
    {
        "name": "productP",
        "price": 999916,
        "quantity": 99,
        "image_url": "https://olshop-proto.sgp1.digitaloceanspaces.com/products/MRAjWwhTHc.png"
    },
    {
        "name": "productQ",
        "price": 999917,
        "quantity": 99,
        "image_url": "https://olshop-proto.sgp1.digitaloceanspaces.com/products/XVlBzgbaiC.png"
    },
    {
        "name": "productR",
        "price": 999918,
        "quantity": 99,
        "image_url": "https://olshop-proto.sgp1.digitaloceanspaces.com/products/MRAjWwhTHc.png"
    },
    {
        "name": "productS",
        "price": 999919,
        "quantity": 99,
        "image_url": "https://olshop-proto.sgp1.digitaloceanspaces.com/products/XVlBzgbaiC.png"
    },
    {
        "name": "productT",
        "price": 999920,
        "quantity": 99,
        "image_url": "https://olshop-proto.sgp1.digitaloceanspaces.com/products/MRAjWwhTHc.png"
    }
]